reactive/__init__.py
reactive/shared.py
reactive/observable/Computed.py
reactive/observable/Reactive.py
reactive/observable/__init__.py
reactive/observer/Watch.py
reactive/observer/WatchAttr.py
reactive/observer/__init__.py
reactive_python-0.2.0.dist-info/LICENSE
reactive_python-0.2.0.dist-info/METADATA
reactive_python-0.2.0.dist-info/WHEEL
reactive_python-0.2.0.dist-info/top_level.txt
reactive_python-0.2.0.dist-info/RECORD
