Metadata-Version: 2.1
Name: reactive-python
Version: 0.2.0
Summary: A simple reactive programming library
Author: yunfan, jiahao
Author-email: bi1lqy.y@gmail.com
License: MIT
License-File: LICENSE
